README.txt
bootstrap.py
buildout.cfg
sbo.spec
setup.py
source.cfg
bootstrap/bootstrap.py
src/zc/__init__.py
src/zc.sbo.egg-info/PKG-INFO
src/zc.sbo.egg-info/SOURCES.txt
src/zc.sbo.egg-info/dependency_links.txt
src/zc.sbo.egg-info/entry_points.txt
src/zc.sbo.egg-info/namespace_packages.txt
src/zc.sbo.egg-info/not-zip-safe
src/zc.sbo.egg-info/requires.txt
src/zc.sbo.egg-info/top_level.txt
src/zc/sbo/__init__.py
src/zc/sbo/sbo.test
src/zc/sbo/tests.py