Metadata-Version: 1.0
Name: zc.sbo
Version: 0.6.1
Summary: System Buildouts
Home-page: UNKNOWN
Author: Jim Fulton
Author-email: jim@zope.com
License: ZPL 2.1
Platform: UNKNOWN
